LICENSE
README.md
setup.py
simple_perception/__init__.py
simple_perception.egg-info/PKG-INFO
simple_perception.egg-info/SOURCES.txt
simple_perception.egg-info/dependency_links.txt
simple_perception.egg-info/requires.txt
simple_perception.egg-info/top_level.txt
simple_perception/camera_only/__init__.py
simple_perception/camera_only/bevformer/__init__.py
simple_perception/camera_only/bevformer/bevformer_tiny/__init__.py
simple_perception/camera_only/bevformer/bevformer_tiny/attention_modules.py
simple_perception/camera_only/bevformer/bevformer_tiny/bevformer.py
simple_perception/camera_only/bevformer/bevformer_tiny/common_modules.py
simple_perception/camera_only/bevformer/bevformer_tiny/config.py
simple_perception/camera_only/bevformer/bevformer_tiny/decoders.py
simple_perception/camera_only/bevformer/bevformer_tiny/encoders.py
simple_perception/camera_only/bevformer/bevformer_tiny/geometry_utils.py
simple_perception/camera_only/bevformer/bevformer_tiny/loss.py
simple_perception/camera_only/bevformer/bevformer_tiny/mocked_img_meta.py
simple_perception/camera_only/bevformer/bevformer_tiny/transformers.py
simple_perception/lidar_only/__init__.py
simple_perception/lidar_only/pointnet2/__init__.py
simple_perception/lidar_only/pointnet2/basic_modules.py
simple_perception/lidar_only/pointnet2/pointnet2.py