Metadata-Version: 2.1
Name: simple-perception
Version: 0.1.0
Summary: Make complicated AV perception algorithms easy to learn, explore and use
Home-page: https://github.com/DerrickXuNu/simple_perception
Author: Runsheng Xu
Author-email: rxx3386@ucla.edu
License: MIT
Keywords: artificial intelligence,autonomous driving,object detection
Classifier: Development Status :: 4 - Beta
Classifier: Intended Audience :: Developers
Classifier: Topic :: Scientific/Engineering :: Artificial Intelligence
Classifier: License :: OSI Approved :: MIT License
Classifier: Programming Language :: Python :: 3.6
License-File: LICENSE
